README.md
setup.py
pygame_text_centering.egg-info/PKG-INFO
pygame_text_centering.egg-info/SOURCES.txt
pygame_text_centering.egg-info/dependency_links.txt
pygame_text_centering.egg-info/requires.txt
pygame_text_centering.egg-info/top_level.txt
pygamecentering/__init__.py
pygamecentering/centering.py
pygamecentering/offset_data_results.json
pygamecentering/offset_linear_regression.py