Metadata-Version: 2.1
Name: pygame-text-centering
Version: 0.20
Summary: A Pygame library to fix Pygame's text-centering!
Home-page: https://github.com/mchen610/pygame-text-centering
Author: Melvin Chen
Author-email: melvinchen610@gmail.com
Requires-Dist: pygame
Requires-Dist: numpy
Requires-Dist: joblib
Requires-Dist: scipy
Requires-Dist: threadpoolctl
Requires-Dist: scikit-learn
